list2tree/LICENSE
list2tree/README.md
list2tree/__init__.py
list2tree/requirements.txt
list2tree/thirdparty.json
list2tree-0.10.dist-info/LICENSE.rst
list2tree-0.10.dist-info/METADATA
list2tree-0.10.dist-info/WHEEL
list2tree-0.10.dist-info/top_level.txt
list2tree-0.10.dist-info/RECORD
