Metadata-Version: 2.1
Name: list2tree
Version: 0.10
Summary: Converts a list of tuples to a nested "family tree dict
Home-page: https://github.com/hansalemaos/list2tree
Author: Johannes Fischer
Author-email: aulasparticularesdealemaosp@gmail.com
License: MIT
Keywords: tree,list,recursive,dict,convert,family tree
Classifier: Development Status :: 4 - Beta
Classifier: Programming Language :: Python :: 3 :: Only
Classifier: Programming Language :: Python :: 3.10
Classifier: Topic :: Software Development :: Libraries :: Python Modules
Classifier: Topic :: Utilities
License-File: LICENSE.rst
Requires-Dist: flatten-any-dict-iterable-or-whatsoever
